mlrl/__init__.py
mlrl/boosting/__init__.py
mlrl/boosting/learners.py
mlrl/boosting/package_info.py
mlrl/boosting/config/__init__.py
mlrl/boosting/config/parameters.py
mlrl/boosting/cython/__init__.py
mlrl/boosting/cython/head_type.cpython-313-x86_64-linux-musl.so
mlrl/boosting/cython/label_binning.cpython-313-x86_64-linux-musl.so
mlrl/boosting/cython/learner.cpython-313-x86_64-linux-musl.so
mlrl/boosting/cython/learner_boomer.cpython-313-x86_64-linux-musl.so
mlrl/boosting/cython/learner_classification.cpython-313-x86_64-linux-musl.so
mlrl/boosting/cython/libmlrlboosting.so
mlrl/boosting/cython/libmlrlboosting.so.0
mlrl/boosting/cython/libmlrlboosting.so.0.15.1
mlrl/boosting/cython/package_info.cpython-313-x86_64-linux-musl.so
mlrl/boosting/cython/post_processor.cpython-313-x86_64-linux-musl.so
mlrl/boosting/cython/prediction.cpython-313-x86_64-linux-musl.so
mlrl/boosting/cython/probability_calibration.cpython-313-x86_64-linux-musl.so
mlrl/boosting/cython/regularization.cpython-313-x86_64-linux-musl.so
mlrl/boosting/testbed/__init__.py
mlrl/boosting/testbed/runnables.py
mlrl/boosting/testbed/experiments/__init__.py
mlrl/boosting/testbed/experiments/output/__init__.py
mlrl/boosting/testbed/experiments/output/probability_calibration/__init__.py
mlrl/boosting/testbed/experiments/output/probability_calibration/extension.py
mlrl/boosting/testbed/experiments/output/probability_calibration/model_isotonic.py
mlrl/boosting/testbed/experiments/output/probability_calibration/model_no.py
mlrl/boosting/testbed/experiments/output/probability_calibration/writer.py
mlrl_boomer.libs/libgcc_s-0cd532bd.so.1
mlrl_boomer.libs/libgomp-8949ffbe.so.1.0.0
mlrl_boomer.libs/libstdc++-5d72f927.so.6.0.33
mlrl_boomer-0.15.1.dist-info/METADATA
mlrl_boomer-0.15.1.dist-info/WHEEL
mlrl_boomer-0.15.1.dist-info/top_level.txt
mlrl_boomer-0.15.1.dist-info/RECORD
mlrl_boomer-0.15.1.dist-info/sboms/auditwheel.cdx.json
